README.md
setup.py
mkYARA.egg-info/PKG-INFO
mkYARA.egg-info/SOURCES.txt
mkYARA.egg-info/dependency_links.txt
mkYARA.egg-info/entry_points.txt
mkYARA.egg-info/requires.txt
mkYARA.egg-info/top_level.txt
mkyara/__init__.py
mkyara/gen.py
mkyara/indentwriter.py
mkyara/yararule.py
mkyara/utils/__init__.py
mkyara/utils/mkyara_tool.py