Metadata-Version: 2.1
Name: mkYARA
Version: 1.0.0
Summary: Generating YARA rules based on binary code
Home-page: UNKNOWN
Author: Jelle Vergeer / Fox-IT
License: GPLv3
Keywords: YARA IDA
Platform: UNKNOWN
Classifier: Development Status :: 5 - Production/Stable
Classifier: Topic :: Software Development :: Libraries :: Python Modules
Classifier: Programming Language :: Python :: 2
Classifier: Programming Language :: Python :: 3
Classifier: License :: OSI Approved :: GNU General Public License v3 (GPLv3)
